{
  "$schema": "https://schemas.wp.org/trunk/theme.json",
  "version": 2,
  "styles": {
		"elements": {
			"link": {
				"typography": {
					"textDecoration": "none"
				},
				":hover": {
					"typography": {
						"textDecoration": "underline"
					}
				},
				":active": {
					"typography": {
						"textDecoration": "underline"
					}
				}
			}
		}
	},
  "settings": {
    "color": {
      "custom": false,
      "customDuotone": false,
      "customGradient": false,
      "defaultGradients": false,
      "defaultPalette": false,
      "duotone": null,
      "palette": [
        {
          "name": "Black",
          "slug": "black",
          "color": "#000"
        },
        {
          "name": "Grey 80%",
          "slug": "grey-80",
          "color": "#45494C"
        },
        {
          "name": "Grey 60%",
          "slug": "grey-60",
          "color": "#6F7376"
        },
        {
          "name": "Grey 50%",
          "slug": "grey-50",
          "color": "#A3A5A7"
        },
        {
          "name": "Grey 30%",
          "slug": "grey-30",
          "color": "#D1D2D3"
        },       
        {
          "name": "Grey 20%",
          "slug": "grey-20",
          "color": "#ECECEC"
        },
        {
          "name": "Grey 10%",
          "slug": "grey-10",
          "color": "#F5F7F8"
        },
        {
          "name": "Grey 5%",
          "slug": "grey-05",
          "color": "#f9f9f9"
        },
        {
          "name": "Beige 30%",
          "slug": "beige-30",
          "color": "#DAD8D1"
        },
        {
          "name": "Beige 20%",
          "slug": "beige-20",
          "color": "#ECEAE4"
        },
        {
          "name": "Beige 10%",
          "slug": "beige-10",
          "color": "#F6F4EF"
        },
        {
          "name": "White",
          "slug": "white",
          "color": "#ffffff"
        },
        {
          "name": "GP NOR Green 2",
          "slug": "gp-nor-green-2",
          "color": "#1F4912"
        },
        {
          "name": "GP NOR Green 3",
          "slug": "gp-nor-green-3",
          "color": "#076c50"
        },
        {
          "name": "GP Green 80",
          "slug": "gp-green-80",
          "color": "#198700"
        },
        {
          "name": "GP Green 70",
          "slug": "gp-green-70",
          "color": "#339E00"
        },
        {
          "name": "GP Green 60",
          "slug": "gp-green-60",
          "color": "#4CB500"
        },
        {
          "name": "GP Green 50",
          "slug": "gp-green-50",
          "color": "#66CC00"
        },
        {
          "name": "GP Green 40",
          "slug": "gp-green-40",
          "color": "#80D643"
        },
        {
          "name": "GP Green 20",
          "slug": "gp-green-20",
          "color": "#B9E696"
        },
        {
          "name": "GP Green 10",
          "slug": "gp-green-10",
          "color": "#D9F1C5"
        },
        {
          "name": "X Dark Blue",
          "slug": "x-dark-blue",
          "color": "#163DB3"
        },
        {
          "name": "Dark Blue",
          "slug": "dark-blue",
          "color": "#2B62C7"
        },
        {
          "name": "Blue",
          "slug": "blue",
          "color": "#4087DA"
        },
        {
          "name": "Blue green",
          "slug": "blue-green",
          "color": "#167F82"
        },
        {
          "name": "Lighter Blue",
          "slug": "ligther-blue",
          "color": "#55ACEE"
        },
        {
          "name": "Light Blue",
          "slug": "blue-20",
          "color": "#b8e0fa"
        },
        {
          "name": "Crimson",
          "slug": "crimson",
          "color": "#e51538"
        },
        {
          "name": "Orange 2",
          "slug": "orange-2",
          "color": "#f36d3a"
        },
        {
          "name": "Orange 1",
          "slug": "orange-1",
          "color": "#fd7e14"
        },
        {
          "name": "Yellow 70",
          "slug": "yellow-70",
          "color": "#FCB600"
        },
        {
          "name": "Yellow 60",
          "slug": "yellow-60",
          "color": "#ffd200"
        },
        {
          "name": "Yellow 50",
          "slug": "yellow-50",
          "color": "#FFE100"
        },
        {
          "name": "Yellow 10",
          "slug": "yellow-10",
          "color": "#FFF6BD"
        }
      ]
    },
    "blocks": {
      "core/button": {
        "border": {
          "radius": false
        }
      },
      "core/heading": {
        "spacing": {
          "margin": true
        }
      },
      "core/group": {
        "spacing": {
          "padding": true
        },
        "border": {
          "radius": true
        }
      },
      "core/table": {
        "color": {
          "text": false,
          "palette": [
            {
              "color": "#f5f7f8",
              "name": "Grey",
              "slug": "grey"
            },
            {
              "color": "#eafee7",
              "name": "Green",
              "slug": "green"
            },
            {
              "color": "#e7f5fe",
              "name": "Blue",
              "slug": "blue"
            }
          ]
        }
      }
    },
    "layout": {
      "contentSize": "736px"
    }
  }
}
